<?xml version="1.0"?>
<!-- Generated by lang::catalog::export_messages_to_file on 2003 February 14 09:22 -->
<message_catalog package_key="dotlrn-static" package_version="0.1a" locale="es_ES" charset="ISO-8859-1">

  <msg key="class_info_portlet_pretty_name">Información de %class_instances_pretty_name%</msg>
  <msg key="community_info_portlet_pretty_name">Información de %clubs_pretty_name%</msg>
  <msg key="Static_HTML_Data">Datos estáticos (HTML)</msg>
  <msg key="subcommunity_info_portlet_pretty_name">Información de %subcommunities_pretty_name%</msg>
</message_catalog>
